neuromancer/README.md
neuromancer/__init__.py
neuromancer/arg.py
neuromancer/callbacks.py
neuromancer/constraint.py
neuromancer/dataset.py
neuromancer/gradients.py
neuromancer/loggers.py
neuromancer/loss.py
neuromancer/plot.py
neuromancer/problem.py
neuromancer/system.py
neuromancer/trainer.py
neuromancer/utils.py
neuromancer/analysis/pwa_maps.py
neuromancer/conf/__init__.py
neuromancer/dynamics/__init__.py
neuromancer/dynamics/integrators.py
neuromancer/dynamics/interpolation.py
neuromancer/dynamics/ode.py
neuromancer/dynamics/physics.py
neuromancer/modules/__init__.py
neuromancer/modules/activations.py
neuromancer/modules/blocks.py
neuromancer/modules/functions.py
neuromancer/modules/rnn.py
neuromancer/modules/solvers.py
neuromancer/psl/__init__.py
neuromancer/psl/autonomous.py
neuromancer/psl/base.py
neuromancer/psl/building_envelope.py
neuromancer/psl/coupled_systems.py
neuromancer/psl/file_emulator.py
neuromancer/psl/gym.py
neuromancer/psl/nonautonomous.py
neuromancer/psl/norms.py
neuromancer/psl/perturb.py
neuromancer/psl/plot.py
neuromancer/psl/signals.py
neuromancer/psl/system_emulator.py
neuromancer/slim/README.md
neuromancer/slim/__init__.py
neuromancer/slim/bench.py
neuromancer/slim/linear.py
neuromancer/slim/rnn.py
neuromancer/slim/butterfly/__init__.py
neuromancer/slim/butterfly/benchmark.py
neuromancer/slim/butterfly/butterfly.py
neuromancer/slim/butterfly/butterfly_multiply.py
neuromancer/slim/butterfly/complex_utils.py
neuromancer/slim/butterfly/permutation.py
neuromancer/slim/butterfly/permutation_multiply.py
neuromancer/slim/butterfly/utils.py
neuromancer/slim/butterfly/factor_multiply/factor_multiply.cpp
neuromancer/slim/butterfly/factor_multiply/factor_multiply_cuda.cu
neuromancer/slim/butterfly/factor_multiply/setup.py
birm_nm_foo-1.5.0.dist-info/LICENSE.md
birm_nm_foo-1.5.0.dist-info/METADATA
birm_nm_foo-1.5.0.dist-info/WHEEL
birm_nm_foo-1.5.0.dist-info/top_level.txt
birm_nm_foo-1.5.0.dist-info/RECORD
