Metadata-Version: 2.1
Name: birm_nm_foo
Version: 1.5.0
Summary: Neural Modules with Adaptive Nonlinear Constraints and Efficient Regularization
Author-email: Aaron Tuor <aaron.tuor@pnnl.gov>, Jan Drgona <jan.drgona@pnnl.gov>, James Koch <james.koch@pnnl.gov>, Madelyn Shapiro <madelyn.shapiro@pnnl.gov>, Rahul Birmiwal <rahul.birmiwal@pnnl.gov>, Draguna Vrabie <draguna.vrabie@pnnl.gov>
License: BSD-2-Clause
Project-URL: homepage, https://github.com/pnnl/neuromancer/
Project-URL: documentation, https://github.com/pnnl/neuromancer/
Project-URL: repository, https://github.com/pnnl/neuromancer/
Keywords: Deep Learning,Pytorch,Linear Models,Dynamical Systems,Data-driven control
Classifier: Programming Language :: Python :: 3.9
Classifier: Programming Language :: Python :: 3.10
Classifier: Topic :: Scientific/Engineering :: Artificial Intelligence
Classifier: Topic :: Scientific/Engineering :: Physics
Classifier: License :: OSI Approved :: BSD License
Requires-Python: <3.11,>=3.9
License-File: LICENSE.md
Requires-Dist: dill
Requires-Dist: graphviz
Requires-Dist: matplotlib
Requires-Dist: mlflow ==2.5.0
Requires-Dist: networkx ==3.0.0
Requires-Dist: numpy <1.24.0
Requires-Dist: pandas
Requires-Dist: plum-dispatch ==1.7.3
Requires-Dist: scikit-learn
Requires-Dist: scipy
Requires-Dist: six
Requires-Dist: pydot ==1.4.2
Requires-Dist: pyts
Requires-Dist: torch
Requires-Dist: torchdiffeq
Requires-Dist: toml
Requires-Dist: lightning
Requires-Dist: cvxpy
Requires-Dist: cvxpylayers
Requires-Dist: casadi
Requires-Dist: wandb
Provides-Extra: docs
Requires-Dist: sphinx ; extra == 'docs'
Requires-Dist: sphinx-rtd-theme ; extra == 'docs'
Provides-Extra: examples
Requires-Dist: casadi ; extra == 'examples'
Requires-Dist: cvxpy ; extra == 'examples'
Requires-Dist: imageio ; extra == 'examples'
Requires-Dist: cvxpylayers ; extra == 'examples'
Provides-Extra: tests
Requires-Dist: pytest ; extra == 'tests'
Requires-Dist: hypothesis ; extra == 'tests'
